quantumdmn/__init__.py
quantumdmn/api_client.py
quantumdmn/api_response.py
quantumdmn/auth.py
quantumdmn/configuration.py
quantumdmn/engine.py
quantumdmn/exceptions.py
quantumdmn/py.typed
quantumdmn/rest.py
quantumdmn/api/__init__.py
quantumdmn/api/default_api.py
quantumdmn/models/__init__.py
quantumdmn/models/add_project_member_request.py
quantumdmn/models/batch_evaluate_design_request.py
quantumdmn/models/batch_evaluation_response.py
quantumdmn/models/batch_evaluation_response_results_inner.py
quantumdmn/models/batch_get_users_request.py
quantumdmn/models/create_definition_request.py
quantumdmn/models/create_project_request.py
quantumdmn/models/create_subscription_upgrade_transaction200_response.py
quantumdmn/models/create_subscription_upgrade_transaction_request.py
quantumdmn/models/credits_quota.py
quantumdmn/models/daily_stat.py
quantumdmn/models/definition.py
quantumdmn/models/definitions_quota.py
quantumdmn/models/error.py
quantumdmn/models/evaluate_design_request.py
quantumdmn/models/evaluate_design_request_kpi_initial_state_value_inner.py
quantumdmn/models/evaluate_design_request_kpi_initial_state_value_inner_metrics_inner.py
quantumdmn/models/evaluate_stored_request.py
quantumdmn/models/evaluation_result.py
quantumdmn/models/execution.py
quantumdmn/models/frontend_config.py
quantumdmn/models/frontend_config_oidc.py
quantumdmn/models/frontend_config_paddle.py
quantumdmn/models/get_customer_portal_session200_response.py
quantumdmn/models/get_health200_response.py
quantumdmn/models/get_version200_response.py
quantumdmn/models/hit_rule.py
quantumdmn/models/kpi_trend.py
quantumdmn/models/kpi_trend_data_inner.py
quantumdmn/models/organization_user.py
quantumdmn/models/overview_response.py
quantumdmn/models/overview_response_stats.py
quantumdmn/models/paginated_definitions_response.py
quantumdmn/models/paginated_executions_response.py
quantumdmn/models/pagination_metadata.py
quantumdmn/models/project.py
quantumdmn/models/project_member.py
quantumdmn_sdk-1.0.0.dist-info/licenses/LICENSE
quantumdmn_sdk-1.0.0.dist-info/METADATA
quantumdmn_sdk-1.0.0.dist-info/WHEEL
quantumdmn_sdk-1.0.0.dist-info/top_level.txt
quantumdmn_sdk-1.0.0.dist-info/RECORD
