Metadata-Version: 2.4
Name: quantumdmn-sdk
Version: 1.0.0
Summary: QuantumDMN Python SDK
Home-page: https://quantumdmn.com
Author: QuantumDMN
Author-email: QuantumDMN <support@quantumdmn.com>
Project-URL: Repository, https://github.com/quantumdmn/dmn-python-sdk
Keywords: QuantumDMN,DMN,dmn engine,Python SDK,BPMN
Requires-Python: >=3.9
License-File: LICENSE
Requires-Dist: urllib3<3.0.0,>=2.1.0
Requires-Dist: python-dateutil>=2.8.2
Requires-Dist: pydantic>=2
Requires-Dist: typing-extensions>=4.7.1
Requires-Dist: PyJWT>=2.8.0
Requires-Dist: requests>=2.31.0
Dynamic: author
Dynamic: home-page
Dynamic: license-file
